hydra/Annotation.py
hydra/Hydra.py
hydra/__init__.py
hydra/model.py
hydra/train.py
hydra/util.py
hydra/R/Process_Dataset.R
hydra/R/UMAP_plot.R
hydra/R/plot_predictions.R
hydra_tools-0.1.0.dist-info/licenses/LICENSE
hydra_tools-0.1.0.dist-info/METADATA
hydra_tools-0.1.0.dist-info/WHEEL
hydra_tools-0.1.0.dist-info/entry_points.txt
hydra_tools-0.1.0.dist-info/top_level.txt
hydra_tools-0.1.0.dist-info/RECORD
