Metadata-Version: 2.4
Name: hydra-tools
Version: 0.1.0
Summary: Thank you for using Hydra 😄, an interpretable deep generative tool for single-cell omics. Please refer to the full documentation available at https://sydneybiox.github.io/Hydra/ for detailed usage instructions. If you encounter any issues running the tool - Please open an issue on Github, and we will get back to you as soon as possible!!
Home-page: https://github.com/SydneyBioX/Hydra
Author: Manoj M Wagle
Author-email: mwag8019@uni.sydney.edu.au
License: MIT
Classifier: Development Status :: 5 - Production/Stable
Classifier: Intended Audience :: Science/Research
Classifier: Topic :: Scientific/Engineering :: Artificial Intelligence
Classifier: Topic :: Scientific/Engineering :: Bio-Informatics
Classifier: License :: OSI Approved :: MIT License
Classifier: Programming Language :: Python :: 3.8
License-File: LICENSE
Requires-Dist: anndata
Requires-Dist: captum
Requires-Dist: h5py
Requires-Dist: libpng-bins
Requires-Dist: torch
Requires-Dist: torchvision
Requires-Dist: torchaudio
Requires-Dist: pandas
Requires-Dist: scipy
Requires-Dist: scikit-learn
Requires-Dist: scanpy
Requires-Dist: tqdm
Requires-Dist: numpy
Requires-Dist: numba
Dynamic: author
Dynamic: author-email
Dynamic: classifier
Dynamic: description
Dynamic: description-content-type
Dynamic: home-page
Dynamic: license
Dynamic: license-file
Dynamic: requires-dist
Dynamic: summary
